pyeasycache/__init__.py
pyeasycache/backend/__init__.py
pyeasycache/backend/disk/__init__.py
pyeasycache/backend/disk/cache.py
pyeasycache/backend/disk/types.py
pyeasycache/backend/redis/__init__.py
pyeasycache/backend/redis/cache.py
pyeasycache/backend/redis/types.py
pyeasycache/core/__init__.py
pyeasycache/core/abc.py
pyeasycache/core/config.py
pyeasycache/core/utils.py
pyeasycache-0.0.1.dist-info/LICENSE
pyeasycache-0.0.1.dist-info/WHEEL
pyeasycache-0.0.1.dist-info/METADATA
pyeasycache-0.0.1.dist-info/RECORD
