Metadata-Version: 2.1
Name: pyeasycache
Version: 0.0.1
Summary: easy python cache
License: Apache-2.0
Author: phi
Author-email: phi.friday@gmail.com
Requires-Python: >=3.8,<4.0
Classifier: Development Status :: 3 - Alpha
Classifier: License :: OSI Approved :: Apache Software License
Classifier: Programming Language :: Python :: 3
Classifier: Programming Language :: Python :: 3 :: Only
Classifier: Programming Language :: Python :: 3.10
Classifier: Programming Language :: Python :: 3.8
Classifier: Programming Language :: Python :: 3.9
Provides-Extra: redis
Requires-Dist: diskcache (>=5.4.0,<6.0.0)
Requires-Dist: pottery (>=3.0.0,<4.0.0); extra == "redis"
Requires-Dist: pydantic (>=1.9.1,<2.0.0)
Requires-Dist: redis (>=4.3.4,<5.0.0); extra == "redis"
